[
  {
    "crn": "28094",
    "course": "AFAM 10",
    "section": "01Y",
    "seats": "Open",
    "title": "An Introduction to African American Studies",
    "days": "·T·····",
    "times": "10:30 AM-12:20 PM",
    "instructor": "Julie Keiffer-Lewis",
    "location": "MLC108",
    "classInfo": "HY"
  },
  {
    "crn": "26996",
    "course": "AFAM 10",
    "section": "60Z",
    "seats": "Open",
    "title": "An Introduction to African American Studies",
    "days": "·······",
    "times": "TBA-TBA",
    "instructor": "Julie Keiffer-Lewis",
    "location": "ONLINE",
    "classInfo": "OL"
  },
  {
    "crn": "27966",
    "course": "AFAM 10",
    "section": "62Z",
    "seats": "Open",
    "title": "An Introduction to African American Studies",
    "days": "·······",
    "times": "TBA-TBA",
    "instructor": "Julie Keiffer-Lewis",
    "location": "ONLINE",
    "classInfo": "OLLQ"
  },
  {
    "crn": "26420",
    "course": "AFAM 12A",
    "section": "60Z",
    "seats": "Open",
    "title": "African American History to 1865",
    "days": "·······",
    "times": "TBA-TBA",
    "instructor": "Julie Keiffer-Lewis",
    "location": "ONLINE",
    "classInfo": "OL"
  },
  {
    "crn": "28586",
    "course": "ASAM 11",
    "section": "01",
    "seats": "Open",
    "title": "Asian Americans and Racism",
    "days": "M·W····",
    "times": "12:30 PM-02:20 PM",
    "instructor": "Bianca Ling",
    "location": "MLC113",
    "classInfo": ""
  },
  {
    "crn": "28730",
    "course": "ASAM 11",
    "section": "02",
    "seats": "Open",
    "title": "Asian Americans and Racism",
    "days": "·T·R···",
    "times": "12:30 PM-02:20 PM",
    "instructor": "CANALES, JUICE",
    "location": "MLC111",
    "classInfo": ""
  },
  {
    "crn": "27800",
    "course": "ASAM 11",
    "section": "60Z",
    "seats": "Open",
    "title": "Asian Americans and Racism",
    "days": "·······",
    "times": "TBA-TBA",
    "instructor": "Nori Henk",
    "location": "ONLINE",
    "classInfo": "OL"
  },
  {
    "crn": "28595",
    "course": "ASAM 11",
    "section": "61Z",
    "seats": "Open",
    "title": "Asian Americans and Racism",
    "days": "·······",
    "times": "TBA-TBA",
    "instructor": "Nina Moskowitz",
    "location": "ONLINE",
    "classInfo": "OL"
  },
  {
    "crn": "28596",
    "course": "ASAM 11",
    "section": "62Z",
    "seats": "Open",
    "title": "Asian Americans and Racism",
    "days": "·······",
    "times": "TBA-TBA",
    "instructor": "Nori Henk",
    "location": "ONLINE",
    "classInfo": "OL"
  },
  {
    "crn": "28597",
    "course": "ASAM 20",
    "section": "61Z",
    "seats": "Open",
    "title": "Asian Pacific American Literature",
    "days": "·······",
    "times": "TBA-TBA",
    "instructor": "Francesca Caparas",
    "location": "ONLINE",
    "classInfo": "OL"
  },
  {
    "crn": "28046",
    "course": "ASAM 40",
    "section": "40",
    "seats": "Open",
    "title": "History of Art: Arts of Asia",
    "days": "M·W····",
    "times": "12:30 PM-02:20 PM",
    "instructor": "So Kam Lee",
    "location": "VPA132",
    "classInfo": ""
  },
  {
    "crn": "25797",
    "course": "ASAM 41",
    "section": "61Z",
    "seats": "Open",
    "title": "Introduction to Korean Popular Culture",
    "days": "·······",
    "times": "TBA-TBA",
    "instructor": "Young Jung",
    "location": "ONLINE",
    "classInfo": "OL"
  },
  {
    "crn": "26997",
    "course": "CETH 8",
    "section": "61Z",
    "seats": "Open",
    "title": "Women of Color in the USA",
    "days": "·······",
    "times": "TBA-TBA",
    "instructor": "Susana Ramirez",
    "location": "ONLINE",
    "classInfo": "OL"
  },
  {
    "crn": "28608",
    "course": "CETH 10",
    "section": "01",
    "seats": "Open",
    "title": "Introduction to Ethnic Studies",
    "days": "M·W····",
    "times": "10:30 AM-12:20 PM",
    "instructor": "",
    "location": "MLC111",
    "classInfo": ""
  },
  {
    "crn": "28609",
    "course": "CETH 10",
    "section": "02",
    "seats": "Open",
    "title": "Introduction to Ethnic Studies",
    "days": "·T·R···",
    "times": "12:30 PM-02:20 PM",
    "instructor": "",
    "location": "L25",
    "classInfo": ""
  },
  {
    "crn": "28610",
    "course": "CETH 10",
    "section": "03",
    "seats": "Open",
    "title": "Introduction to Ethnic Studies",
    "days": "M·W····",
    "times": "01:30 PM-03:20 PM",
    "instructor": "",
    "location": "L81",
    "classInfo": ""
  },
  {
    "crn": "28096",
    "course": "CETH 10",
    "section": "62Z",
    "seats": "Open",
    "title": "Introduction to Ethnic Studies",
    "days": "·······",
    "times": "TBA-TBA",
    "instructor": "Angelina Loyola",
    "location": "ONLINE",
    "classInfo": "OL"
  },
  {
    "crn": "26399",
    "course": "CETH 10",
    "section": "63Z",
    "seats": "Open",
    "title": "Introduction to Ethnic Studies",
    "days": "·······",
    "times": "TBA-TBA",
    "instructor": "Angelina Loyola",
    "location": "ONLINE",
    "classInfo": "OL"
  },
  {
    "crn": "28316",
    "course": "CETH 10",
    "section": "64Z",
    "seats": "Open",
    "title": "Introduction to Ethnic Studies",
    "days": "·······",
    "times": "TBA-TBA",
    "instructor": "David Palaita",
    "location": "ONLINE",
    "classInfo": "OL"
  },
  {
    "crn": "28385",
    "course": "CETH 10",
    "section": "65Z",
    "seats": "Open",
    "title": "Introduction to Ethnic Studies",
    "days": "·······",
    "times": "TBA-TBA",
    "instructor": "TAN, NATHANIEL",
    "location": "ONLINE",
    "classInfo": "OL"
  },
  {
    "crn": "28602",
    "course": "CETH 10",
    "section": "66Z",
    "seats": "Open",
    "title": "Introduction to Ethnic Studies",
    "days": "·······",
    "times": "TBA-TBA",
    "instructor": "TAN, NATHANIEL",
    "location": "ONLINE",
    "classInfo": "OL"
  },
  {
    "crn": "28604",
    "course": "CETH 10",
    "section": "67Z",
    "seats": "Open",
    "title": "Introduction to Ethnic Studies",
    "days": "·······",
    "times": "TBA-TBA",
    "instructor": "Majel Boxer",
    "location": "ONLINE",
    "classInfo": "OL"
  },
  {
    "crn": "26402",
    "course": "CETH 29",
    "section": "65Z",
    "seats": "Open",
    "title": "Ethnic Studies, Cultural Pluralism, and American Law and Justice",
    "days": "·······",
    "times": "TBA-TBA",
    "instructor": "Meghan Kensler",
    "location": "ONLINE",
    "classInfo": "OL"
  },
  {
    "crn": "28312",
    "course": "CHLX 10",
    "section": "01Y",
    "seats": "Open",
    "title": "Introduction to Chicanx and Latinx Studies",
    "days": "·T·····",
    "times": "10:00 AM-11:50 AM",
    "instructor": "Angelica Esquivel Moreno",
    "location": "MLC112",
    "classInfo": "HY"
  },
  {
    "crn": "28089",
    "course": "CHLX 10",
    "section": "40",
    "seats": "Open",
    "title": "Introduction to Chicanx and Latinx Studies",
    "days": "M·W····",
    "times": "12:30 PM-02:20 PM",
    "instructor": "Angelica Esquivel Moreno",
    "location": "L61",
    "classInfo": ""
  },
  {
    "crn": "27018",
    "course": "CHLX 10",
    "section": "60Z",
    "seats": "Open",
    "title": "Introduction to Chicanx and Latinx Studies",
    "days": "·······",
    "times": "TBA-TBA",
    "instructor": "Felipe Ponce",
    "location": "ONLINE",
    "classInfo": "OL"
  },
  {
    "crn": "27340",
    "course": "CHLX 10",
    "section": "61Z",
    "seats": "Open",
    "title": "Introduction to Chicanx and Latinx Studies",
    "days": "·······",
    "times": "TBA-TBA",
    "instructor": "Angelica Esquivel Moreno",
    "location": "ONLINE",
    "classInfo": "OL"
  },
  {
    "crn": "28054",
    "course": "CHLX 12",
    "section": "60Z",
    "seats": "Open",
    "title": "Chicanx and Latinx History",
    "days": "·······",
    "times": "TBA-TBA",
    "instructor": "Angelica Esquivel Moreno",
    "location": "ONLINE",
    "classInfo": "OL"
  },
  {
    "crn": "26486",
    "course": "ICS 25",
    "section": "50Z",
    "seats": "Open",
    "title": "Grassroots Democracy: Race, Politics and the American Promise",
    "days": "·······",
    "times": "TBA-TBA",
    "instructor": "Laura Chin",
    "location": "ONLINE",
    "classInfo": "OL"
  },
  {
    "crn": "27057",
    "course": "ICS 27",
    "section": "1EZ",
    "seats": "Open",
    "title": "Grassroots Democracy: Leadership and Power",
    "days": "·T·R···",
    "times": "06:00 PM-07:50 PM",
    "instructor": "Cynthia Kaufman",
    "location": "ONLINE",
    "classInfo": "OL"
  },
  {
    "crn": "28015",
    "course": "ICS 77",
    "section": "65R",
    "seats": "Open",
    "title": "Special Projects in Intercultural Studies",
    "days": "·······",
    "times": "TBA-TBA",
    "instructor": "",
    "location": "ONLINE",
    "classInfo": ""
  },
  {
    "crn": "28104",
    "course": "ICS 77X",
    "section": "65R",
    "seats": "Open",
    "title": "Special Projects in Intercultural Studies",
    "days": "·······",
    "times": "TBA-TBA",
    "instructor": "",
    "location": "ONLINE",
    "classInfo": ""
  },
  {
    "crn": "28105",
    "course": "ICS 78W",
    "section": "65R",
    "seats": "Open",
    "title": "Special Group Projects in Intercultural Studies",
    "days": "·······",
    "times": "TBA-TBA",
    "instructor": "",
    "location": "ONLINE",
    "classInfo": ""
  },
  {
    "crn": "28106",
    "course": "ICS 78X",
    "section": "65R",
    "seats": "Open",
    "title": "Special Group Projects in Intercultural Studies",
    "days": "·······",
    "times": "TBA-TBA",
    "instructor": "",
    "location": "ONLINE",
    "classInfo": ""
  },
  {
    "crn": "27950",
    "course": "ICS 80X",
    "section": "65R",
    "seats": "Open",
    "title": "Community Based Learning in Intercultural Studies - Intrapersonal",
    "days": "·······",
    "times": "TBA-TBA",
    "instructor": "Cynthia Kaufman",
    "location": "ONLINE",
    "classInfo": ""
  },
  {
    "crn": "28103",
    "course": "ICS 81X",
    "section": "65R",
    "seats": "Open",
    "title": "Community Based Learning in Intercultural Studies - Interpersonal",
    "days": "·······",
    "times": "TBA-TBA",
    "instructor": "Cynthia Kaufman",
    "location": "ONLINE",
    "classInfo": ""
  },
  {
    "crn": "27952",
    "course": "ICS 82X",
    "section": "65R",
    "seats": "Open",
    "title": "Community Based Learning in Intercultural Studies - Systems",
    "days": "·······",
    "times": "TBA-TBA",
    "instructor": "Cynthia Kaufman",
    "location": "ONLINE",
    "classInfo": ""
  },
  {
    "crn": "26403",
    "course": "NAIS 12",
    "section": "60Z",
    "seats": "Open",
    "title": "Ethnic Studies and the Historical Experiences of Native Americans",
    "days": "·······",
    "times": "TBA-TBA",
    "instructor": "Meghan Kensler",
    "location": "ONLINE",
    "classInfo": "OL"
  },
  {
    "crn": "27906",
    "course": "NAIS 31",
    "section": "01Y",
    "seats": "Open",
    "title": "Ethnic Studies: Native Hawaiian and Pacific Islander Experiences",
    "days": "M······",
    "times": "11:30 AM-01:20 PM",
    "instructor": "David Palaita",
    "location": "MCC-10",
    "classInfo": "HY"
  },
  {
    "crn": "27905",
    "course": "NAIS 31",
    "section": "02V",
    "seats": "Open",
    "title": "Ethnic Studies: Native Hawaiian and Pacific Islander Experiences",
    "days": "M······",
    "times": "11:30 AM-01:20 PM",
    "instructor": "David Palaita",
    "location": "MCC-10",
    "classInfo": ""
  }
]